Workbook

Sheet CATÁLOGO
A1: Nº | B1: Nicho | C1: Produto | D1: Descrição | E1: SKU / Código | F1: Estoque | G1: Preço de Venda | H1: Imagem / Arquivo | I1: Custo do Fornecedor | J1: Frete do Fornecedor | K1: Custo Efetivo | L1: Multiplicador | M1: Preço Final do Site | N1: Lucro Bruto Estimado | O1: Margem Bruta | P1: Status de Preço | Q1: Observação Comercial | R1: Imagem do Produto | S1: Reserva de Taxas (%) | T1: Reserva de Taxas (R$) | U1: Lucro Estimado Após Taxas | V1: Margem Estimada Após Taxas
A2: 1 | B2: Fones e Áudio | C2: Headphone Bluetooth Dobrável | D2: Headphone Bluetooth com almofadas acolchoadas | E2: FONE-HEADPHONE-001 | F2: Sob encomenda | G2: 179.9 | H2: assets/produtos/AUDIO-FONE-HEADPHONE-001.jpg | I2: 129.9 | J2: 0 | K2: =I2+J2 | L2: 1.36 | M2: 179.9 | N2: =M2-K2 | O2: =IFERROR(N2/M2,0) | P2: ATIVO - PREÇO DE TESTE | Q2: Margem moderada para manter competitividade e segurança. | S2: 0.05 | T2: =M2*S2 | U2: =M2-K2-T2 | V2: =IFERROR(U2/M2,0)
A3: 2 | B3: Suportes Veiculares | C3: Suporte Veicular 360° | D3: Suporte articulado para celular com base de fixação | E3: SUPORTE-VEICULAR-001 | F3: Sob encomenda | G3: 99.9 | H3: assets/produtos/SUPORTE-SUPORTE-VEICULAR-001.jpg | I3: 69.9 | J3: 0 | K3: =I3+J3 | L3: 1.42 | M3: 99.9 | N3: =M3-K3 | O3: =IFERROR(N3/M3,0) | P3: ATIVO - PREÇO DE TESTE | Q3: Preço competitivo de lançamento com margem intermediária. | S3: 0.05 | T3: =M3*S3 | U3: =M3-K3-T3 | V3: =IFERROR(U3/M3,0)
A4: 3 | B4: Fones e Áudio | C4: Fone Bluetooth i7S TWS | D4: Fone sem fio com estojo de carregamento | E4: FONE-I7S-001 | F4: Sob encomenda | G4: 59.9 | H4: assets/produtos/AUDIO-FONE-I7S-001.jpg | I4: 39.9 | J4: 0 | K4: =I4+J4 | L4: 1.48 | M4: 59.9 | N4: =M4-K4 | O4: =IFERROR(N4/M4,0) | P4: ATIVO - PREÇO DE TESTE | Q4: Preço competitivo de lançamento com margem intermediária. | S4: 0.05 | T4: =M4*S4 | U4: =M4-K4-T4 | V4: =IFERROR(U4/M4,0)
A5: 4 | B5: Proteção e Vestuário | C5: Capa Impermeável para Sapatos | D5: Proteção reutilizável contra água e sujeira | E5: PROTECAO-SAPATO-001 | F5: Sob encomenda | G5: 59.9 | H5: assets/produtos/PROTECAO-PROTECAO-SAPATO-001.jpg | I5: 39.9 | J5: 0 | K5: =I5+J5 | L5: 1.48 | M5: 59.9 | N5: =M5-K5 | O5: =IFERROR(N5/M5,0) | P5: ATIVO - PREÇO DE TESTE | Q5: Preço competitivo de lançamento com margem intermediária. | S5: 0.05 | T5: =M5*S5 | U5: =M5-K5-T5 | V5: =IFERROR(U5/M5,0)
A6: 5 | B6: Proteção e Vestuário | C6: Sobrebota Impermeável Reforçada | D6: Proteção impermeável de cano alto | E6: PROTECAO-SOBREBOTA-001 | F6: Sob encomenda | G6: 74.9 | H6: assets/produtos/PROTECAO-PROTECAO-SOBREBOTA-001.jpg | I6: 49.9 | J6: 0 | K6: =I6+J6 | L6: 1.48 | M6: 74.9 | N6: =M6-K6 | O6: =IFERROR(N6/M6,0) | P6: ATIVO - PREÇO DE TESTE | Q6: Preço competitivo de lançamento com margem intermediária. | S6: 0.05 | T6: =M6*S6 | U6: =M6-K6-T6 | V6: =IFERROR(U6/M6,0)
A7: 6 | B7: Limpeza e Ferramentas | C7: Lavadora Portátil a Bateria | D7: Kit de limpeza com mangueira, bateria e acessórios | E7: LIMPEZA-LAVADORA-001 | F7: Sob encomenda | G7: 454.9 | H7: assets/produtos/LIMPEZA-LIMPEZA-LAVADORA-001.jpg | I7: 349.9 | J7: 0 | K7: =I7+J7 | L7: 1.3 | M7: 454.9 | N7: =M7-K7 | O7: =IFERROR(N7/M7,0) | P7: ATIVO - PREÇO DE TESTE | Q7: Margem mais enxuta devido ao ticket alto; foco em conversão. | S7: 0.05 | T7: =M7*S7 | U7: =M7-K7-T7 | V7: =IFERROR(U7/M7,0)
A8: 7 | B8: Segurança Veicular | C8: Trava de Disco com Alarme | D8: Cadeado para moto com sistema de alarme | E8: SEGURANCA-TRAVA-DISCO-001 | F8: Sob encomenda | G8: 129.9 | H8: assets/produtos/SEGURANCA-SEGURANCA-TRAVA-DISCO-001.jpg | I8: 89.9 | J8: 0 | K8: =I8+J8 | L8: 1.42 | M8: 129.9 | N8: =M8-K8 | O8: =IFERROR(N8/M8,0) | P8: ATIVO - PREÇO DE TESTE | Q8: Preço competitivo de lançamento com margem intermediária. | S8: 0.05 | T8: =M8*S8 | U8: =M8-K8-T8 | V8: =IFERROR(U8/M8,0)
A9: 8 | B9: Limpeza e Casa | C9: Mini Aspirador Portátil | D9: Aspirador compacto para teclado, carro e cantos | E9: LIMPEZA-ASPIRADOR-001 | F9: Sob encomenda | G9: 144.9 | H9: assets/produtos/LIMPEZA-LIMPEZA-ASPIRADOR-001.jpg | I9: 99.9 | J9: 0 | K9: =I9+J9 | L9: 1.42 | M9: 144.9 | N9: =M9-K9 | O9: =IFERROR(N9/M9,0) | P9: ATIVO - PREÇO DE TESTE | Q9: Preço competitivo de lançamento com margem intermediária. | S9: 0.05 | T9: =M9*S9 | U9: =M9-K9-T9 | V9: =IFERROR(U9/M9,0)
A10: 9 | B10: Limpeza e Casa | C10: Aspirador Portátil 2 em 1 | D10: Aspirador compacto com bocais para diferentes superfícies | E10: LIMPEZA-ASPIRADOR-002 | F10: Sob encomenda | G10: 164.9 | H10: assets/produtos/LIMPEZA-LIMPEZA-ASPIRADOR-002.jpg | I10: 119.9 | J10: 0 | K10: =I10+J10 | L10: 1.36 | M10: 164.9 | N10: =M10-K10 | O10: =IFERROR(N10/M10,0) | P10: ATIVO - PREÇO DE TESTE | Q10: Margem moderada para manter competitividade e segurança. | S10: 0.05 | T10: =M10*S10 | U10: =M10-K10-T10 | V10: =IFERROR(U10/M10,0)
A11: 10 | B11: Proteção e Vestuário | C11: Luvas Antiderrapantes | D11: Luvas para proteção e atividades do dia a dia | E11: PROTECAO-LUVAS-001 | F11: Sob encomenda | G11: 54.9 | H11: assets/produtos/PROTECAO-PROTECAO-LUVAS-001.jpg | I11: 34.9 | J11: 0 | K11: =I11+J11 | L11: 1.48 | M11: 54.9 | N11: =M11-K11 | O11: =IFERROR(N11/M11,0) | P11: ATIVO - PREÇO DE TESTE | Q11: Preço competitivo de lançamento com margem intermediária. | S11: 0.05 | T11: =M11*S11 | U11: =M11-K11-T11 | V11: =IFERROR(U11/M11,0)
A12: 11 | B12: Limpeza e Ferramentas | C12: Pistola de Limpeza Portátil | D12: Kit para limpeza e lavagem de superfícies e veículos | E12: LIMPEZA-PISTOLA-001 | F12: Sob encomenda | G12: 219.9 | H12: assets/produtos/LIMPEZA-LIMPEZA-PISTOLA-001.jpg | I12: 159.9 | J12: 0 | K12: =I12+J12 | L12: 1.36 | M12: 219.9 | N12: =M12-K12 | O12: =IFERROR(N12/M12,0) | P12: ATIVO - PREÇO DE TESTE | Q12: Margem moderada para manter competitividade e segurança. | S12: 0.05 | T12: =M12*S12 | U12: =M12-K12-T12 | V12: =IFERROR(U12/M12,0)
A13: 12 | B13: Acessórios para Casa | C13: Organizador Adesivo Multifuncional | D13: Suporte adesivo compacto para pequenos objetos | E13: CASA-ORGANIZADOR-001 | F13: Sob encomenda | G13: 44.9 | H13: assets/produtos/ACESSORIO-CASA-ORGANIZADOR-001.jpg | I13: 29.9 | J13: 0 | K13: =I13+J13 | L13: 1.48 | M13: 44.9 | N13: =M13-K13 | O13: =IFERROR(N13/M13,0) | P13: ATIVO - PREÇO DE TESTE | Q13: Preço competitivo de lançamento com margem intermediária. | S13: 0.05 | T13: =M13*S13 | U13: =M13-K13-T13 | V13: =IFERROR(U13/M13,0)
... A28: 27 | B28: Fones e Áudio | C28: Fone Bluetooth i12 | D28: Fone sem fio com estojo de carregamento | E28: FONE-I12-001 | F28: Sob encomenda | G28: 74.9 | H28: assets/produtos/AUDIO-FONE-I12-001.jpg | I28: 49.9 | J28: 0 | K28: =I28+J28 | L28: 1.48 | M28: 74.9 | N28: =M28-K28 | O28: =IFERROR(N28/M28,0) | P28: ATIVO - PREÇO DE TESTE | Q28: Preço competitivo de lançamento com margem intermediária. | S28: 0.05 | T28: =M28*S28 | U28: =M28-K28-T28 | V28: =IFERROR(U28/M28,0)

Sheet VALIDAÇÃO
A1: Item | B1: Status
A2: Produtos cadastrados | B2: 27
A3: Imagens vinculadas | B3: 27
A4: Arquivos de imagem sem nome aleatório | B4: OK
A5: SKU vinculado ao produto | B5: OK
A6: Base do site | B6: Pacote original da Ítalo modificado
A7: Modelo de preço | B7: Preço do fornecedor = custo; preço final calculado por faixa de multiplicador
A8: Custo efetivo | B8: Custo do fornecedor + frete do fornecedor (frete atualmente R$ 0,00 por falta de valor informado)
A9: Preço final no site | B9: Sincronizado com app.js

Sheet PRECIFICAÇÃO
A1: CONFIGURAÇÃO DE PREÇOS — BASE DE TESTE / MARGEM INTERMEDIÁRIA
A2: Faixa de custo | B2: Multiplicador | C2: Estratégia
A3: Até R$ 20,00 | B3: 1.6 | C3: Proteção mínima para itens baratos e taxas fixas.
A4: R$ 20,01 a R$ 50,00 | B4: 1.48 | C4: Preço de entrada competitivo.
A5: R$ 50,01 a R$ 100,00 | B5: 1.42 | C5: Margem intermediária para início da operação.
A6: R$ 100,01 a R$ 200,00 | B6: 1.36 | C6: Margem moderada para manter conversão.
A7: Acima de R$ 200,00 | B7: 1.3 | C7: Margem mais enxuta para ticket alto.
A9: RESERVA DE TAXAS | B9: 0.05 | C9: Reserva-base de 5% para taxas de pagamento. Ajustável quando o gateway real estiver definido.
A10: FRETE DO FORNECEDOR | B10: R$ 0,00 | C10: Mantido em zero porque não foi informado frete individual do fornecedor.
A11: LÓGICA | C11: Preço final = custo efetivo × multiplicador, arredondado para preço psicológico. Lucro estimado após taxas desconta 5% do preço de venda.

Sheet RESUMO
A1: RESUMO COMERCIAL — PREÇOS DE TESTE
A2: Indicador | B2: Valor
A3: Produtos ativos | B3: =COUNTA(CATÁLOGO!C2:C28)
A4: Custo total de 1 unidade de cada produto | B4: =SUM(CATÁLOGO!K2:K28)
A5: Receita potencial com 1 unidade de cada produto | B5: =SUM(CATÁLOGO!M2:M28)
A6: Lucro bruto potencial | B6: =SUM(CATÁLOGO!N2:N28)
A7: Reserva total estimada para taxas | B7: =SUM(CATÁLOGO!T2:T28)
A8: Lucro estimado após reserva de taxas | B8: =SUM(CATÁLOGO!U2:U28)
A9: Margem média estimada após taxas | B9: =AVERAGE(CATÁLOGO!V2:V28)
